flask_zipper
